<?xml version="1.0" encoding="UTF-8"?>
<!DOCTYPE mapper PUBLIC "-//mybatis.org//DTD Mapper 3.0//EN" "http://mybatis.org/dtd/mybatis-3-mapper.dtd">
<mapper namespace="com.jingchao.mybatis.mapper.EmpMapper">
  <resultMap id="BaseResultMap" type="com.jingchao.mybatis.pojo.Emp">
    <!--
      WARNING - @mbg.generated
      This element is automatically generated by MyBatis Generator, do not modify.
      This element was generated on Sun Sep 04 15:02:13 CST 2022.
    -->
    <id column="emp_id" jdbcType="INTEGER" property="empId" />
    <result column="emp_name" jdbcType="VARCHAR" property="empName" />
    <result column="age" jdbcType="INTEGER" property="age" />
    <result column="gender" jdbcType="CHAR" property="gender" />
    <result column="dept_id" jdbcType="INTEGER" property="deptId" />
  </resultMap>
  <delete id="deleteByPrimaryKey" parameterType="java.lang.Integer">
    <!--
      WARNING - @mbg.generated
      This element is automatically generated by MyBatis Generator, do not modify.
      This element was generated on Sun Sep 04 15:02:13 CST 2022.
    -->
    delete from t_emp
    where emp_id = #{empId,jdbcType=INTEGER}
  </delete>
  <insert id="insert" parameterType="com.jingchao.mybatis.pojo.Emp">
    <!--
      WARNING - @mbg.generated
      This element is automatically generated by MyBatis Generator, do not modify.
      This element was generated on Sun Sep 04 15:02:13 CST 2022.
    -->
    insert into t_emp (emp_id, emp_name, age, 
      gender, dept_id)
    values (#{empId,jdbcType=INTEGER}, #{empName,jdbcType=VARCHAR}, #{age,jdbcType=INTEGER}, 
      #{gender,jdbcType=CHAR}, #{deptId,jdbcType=INTEGER})
  </insert>
  <update id="updateByPrimaryKey" parameterType="com.jingchao.mybatis.pojo.Emp">
    <!--
      WARNING - @mbg.generated
      This element is automatically generated by MyBatis Generator, do not modify.
      This element was generated on Sun Sep 04 15:02:13 CST 2022.
    -->
    update t_emp
    set emp_name = #{empName,jdbcType=VARCHAR},
      age = #{age,jdbcType=INTEGER},
      gender = #{gender,jdbcType=CHAR},
      dept_id = #{deptId,jdbcType=INTEGER}
    where emp_id = #{empId,jdbcType=INTEGER}
  </update>
  <select id="selectByPrimaryKey" parameterType="java.lang.Integer" resultMap="BaseResultMap">
    <!--
      WARNING - @mbg.generated
      This element is automatically generated by MyBatis Generator, do not modify.
      This element was generated on Sun Sep 04 15:02:13 CST 2022.
    -->
    select emp_id, emp_name, age, gender, dept_id
    from t_emp
    where emp_id = #{empId,jdbcType=INTEGER}
  </select>
  <select id="selectAll" resultMap="BaseResultMap">
    <!--
      WARNING - @mbg.generated
      This element is automatically generated by MyBatis Generator, do not modify.
      This element was generated on Sun Sep 04 15:02:13 CST 2022.
    -->
    select emp_id, emp_name, age, gender, dept_id
    from t_emp
  </select>
</mapper>